M2_ProposalTools/FilterImages.py
M2_ProposalTools/M2_vis_plot_year.py
M2_ProposalTools/MakeRMSmap.py
M2_ProposalTools/ModelFitting.py
M2_ProposalTools/WorkHorse.py
M2_ProposalTools/__init__.py
M2_ProposalTools/analytic_integrations.py
M2_ProposalTools/make_el_chart.py
M2_ProposalTools/numerical_integration.py
M2_ProposalTools/py.typed
M2_ProposalTools/xfer_Function_2p5_21Aonly_PCA5_0f08Filtering.txt
M2_ProposalTools/xfer_Function_3p0_21Aonly_PCA5_0f08Filtering.txt
M2_ProposalTools/xfer_Function_3p5_21Aonly_PCA5_0f08Filtering.txt
M2_ProposalTools/xfer_Function_4p0_21Aonly_PCA5_0f08Filtering.txt
M2_ProposalTools/xfer_Function_4p5_21Aonly_PCA5_0f08Filtering.txt
M2_ProposalTools/xfer_Function_5p0_21Aonly_PCA5_0f08Filtering.txt
M2_TJ-1.2.2.dist-info/LICENSE
M2_TJ-1.2.2.dist-info/METADATA
M2_TJ-1.2.2.dist-info/WHEEL
M2_TJ-1.2.2.dist-info/top_level.txt
M2_TJ-1.2.2.dist-info/RECORD
